setup.py
bin/brickmason
bin/mason
brickmason/__init__.py
brickmason.egg-info/PKG-INFO
brickmason.egg-info/SOURCES.txt
brickmason.egg-info/dependency_links.txt
brickmason.egg-info/not-zip-safe
brickmason.egg-info/requires.txt
brickmason.egg-info/top_level.txt
brickmason/driver/__init__.py
brickmason/driver/greenbutton.py
brickmason/driver/haystack.py
brickmason/driver/ifc.py
brickmason/driver/nationalweatherservice.py
brickmason/driver/revit.py
brickmason/driver/revit_door.py
brickmason/driver/site.py
brickmason/driver/ttlfile.py
brickmason/driver/xbosbuildingmeter.py
brickmason/driver/xboshamilton.py
brickmason/driver/xbosinterfaces.py
brickmason/driver/xboslight.py
brickmason/driver/xbosmeter.py
brickmason/driver/xbosplug.py
brickmason/driver/xbosthermostat.py
brickmason/driver/pythonifc/__init__.py
brickmason/driver/pythonifc/ifcfilereader.py
brickmason/driver/pythonifc/ifcfreecad.py
brickmason/driver/pythonifc/ifcschemareader.py
brickmason/ontologies/__init__.py