Metadata-Version: 1.0
Name: brickmason
Version: 0.0.2
Summary: Brick generation
Home-page: https://github.com/SoftwareDefinedBuildings/XBOS
Author: Gabe Fierro
Author-email: gtfierro@cs.berkeley.edu
License: UNKNOWN
Platform: UNKNOWN
